<?xml version='1.0' encoding='utf-8'?>
<mujoco model="CF2 scene">
  <include file="cf2.xml" />
  <statistic center="0 0 0.1" extent="0.2" meansize=".05" />
  <visual>
    <headlight diffuse="0.8 0.8 0.8" ambient="0.5 0.5 0.5" specular="0.2 0.2 0.2" />
    <rgba haze="0.9 0.9 0.95 1" />
    <global azimuth="-20" elevation="-20" ellipsoidinertia="true" />
  </visual>
  <asset>
    <texture type="skybox" builtin="gradient" rgb1="0.6 0.7 0.9" rgb2="0.9 0.9 0.95" width="512" height="3072" />
    <texture type="2d" name="groundplane" builtin="checker" mark="edge" rgb1="0.3 0.35 0.4" rgb2="0.2 0.25 0.3" markrgb="0.8 0.8 0.8" width="300" height="300" />
    <material name="groundplane" texture="groundplane" texuniform="true" texrepeat="5 5" reflectance="0.2" />
  </asset>
  <worldbody>
    <light pos="0 0 1.5" dir="0 0 -1" directional="true" />
    <geom name="floor" size="0 0 0.05" type="plane" material="groundplane" />
    <geom name="dynamic_obs_0" type="cylinder" size="0.025 0.75" pos="1.27973 -0.210648 0.75" quat="1 0 0 0" contype="0" conaffinity="0" rgba="0.82 0.26 0.26 1" />
    <geom name="dynamic_obs_1" type="box" size="0.025 0.025 0.75" pos="1.37803 0.952522 0.75" quat="1 0 0 0" contype="0" conaffinity="0" rgba="0.2 0.62 0.4 1" />
    <geom name="dynamic_obs_2" type="cylinder" size="0.025 0.75" pos="1.51644 0.68154 0.75" quat="1 0 0 0" contype="0" conaffinity="0" rgba="0.22 0.42 0.8 1" />
    <geom name="dynamic_obs_3" type="box" size="0.025 0.025 0.75" pos="1.06855 -0.816858 0.75" quat="1 0 0 0" contype="0" conaffinity="0" rgba="0.84 0.68 0.2 1" />
    <geom name="dynamic_obs_4" type="cylinder" size="0.025 0.75" pos="1.68202 0.859883 0.75" quat="1 0 0 0" contype="0" conaffinity="0" rgba="0.58 0.32 0.78 1" />
    <geom name="dynamic_obs_5" type="box" size="0.025 0.025 0.75" pos="1.55069 -0.77309 0.75" quat="1 0 0 0" contype="0" conaffinity="0" rgba="0.14 0.64 0.7 1" />
    <geom name="dynamic_obs_6" type="cylinder" size="0.025 0.75" pos="1.15729 -0.037727 0.75" quat="1 0 0 0" contype="0" conaffinity="0" rgba="0.82 0.26 0.26 1" />
    <geom name="dynamic_obs_7" type="box" size="0.025 0.025 0.75" pos="1.91264 0.206151 0.75" quat="1 0 0 0" contype="0" conaffinity="0" rgba="0.2 0.62 0.4 1" />
    <geom name="dynamic_obs_8" type="cylinder" size="0.025 0.75" pos="1.8296 0.704812 0.75" quat="1 0 0 0" contype="0" conaffinity="0" rgba="0.22 0.42 0.8 1" />
    <geom name="dynamic_obs_9" type="box" size="0.025 0.025 0.75" pos="1.82969 -0.0798251 0.75" quat="1 0 0 0" contype="0" conaffinity="0" rgba="0.84 0.68 0.2 1" />
    <geom name="dynamic_obs_10" type="cylinder" size="0.025 0.75" pos="1.46818 -0.298175 0.75" quat="1 0 0 0" contype="0" conaffinity="0" rgba="0.58 0.32 0.78 1" />
    <geom name="dynamic_obs_11" type="box" size="0.025 0.025 0.75" pos="1.16801 -0.590129 0.75" quat="1 0 0 0" contype="0" conaffinity="0" rgba="0.14 0.64 0.7 1" />
    <geom name="dynamic_obs_12" type="cylinder" size="0.025 0.75" pos="1.69929 0.203657 0.75" quat="1 0 0 0" contype="0" conaffinity="0" rgba="0.82 0.26 0.26 1" />
    <geom name="dynamic_obs_13" type="box" size="0.025 0.025 0.75" pos="1.36964 0.383976 0.75" quat="1 0 0 0" contype="0" conaffinity="0" rgba="0.2 0.62 0.4 1" />
    <geom name="dynamic_obs_14" type="cylinder" size="0.025 0.75" pos="1.5164 -0.494875 0.75" quat="1 0 0 0" contype="0" conaffinity="0" rgba="0.22 0.42 0.8 1" />
    <geom name="dynamic_obs_15" type="box" size="0.025 0.025 0.75" pos="1.7799 -0.673188 0.75" quat="1 0 0 0" contype="0" conaffinity="0" rgba="0.84 0.68 0.2 1" />
    <geom name="dynamic_obs_16" type="cylinder" size="0.025 0.75" pos="1.37934 0.728058 0.75" quat="1 0 0 0" contype="0" conaffinity="0" rgba="0.58 0.32 0.78 1" />
    <geom name="dynamic_obs_17" type="box" size="0.025 0.025 0.75" pos="1.07899 0.93406 0.75" quat="1 0 0 0" contype="0" conaffinity="0" rgba="0.14 0.64 0.7 1" />
    <geom name="dynamic_obs_18" type="cylinder" size="0.025 0.75" pos="1.58683 0.429735 0.75" quat="1 0 0 0" contype="0" conaffinity="0" rgba="0.82 0.26 0.26 1" />
    <geom name="dynamic_obs_19" type="box" size="0.025 0.025 0.75" pos="1.06245 0.790505 0.75" quat="1 0 0 0" contype="0" conaffinity="0" rgba="0.2 0.62 0.4 1" />
  </worldbody>
</mujoco>